odoo/addons/sequence_reset_period/README.rst
odoo/addons/sequence_reset_period/__init__.py
odoo/addons/sequence_reset_period/__manifest__.py
odoo/addons/sequence_reset_period/models/__init__.py
odoo/addons/sequence_reset_period/models/ir_sequence.py
odoo/addons/sequence_reset_period/static/description/icon.png
odoo/addons/sequence_reset_period/tests/__init__.py
odoo/addons/sequence_reset_period/tests/test_period.py
odoo/addons/sequence_reset_period/views/sequence_views.xml
odoo11_addon_sequence_reset_period-11.0.1.0.0.dist-info/DESCRIPTION.rst
odoo11_addon_sequence_reset_period-11.0.1.0.0.dist-info/METADATA
odoo11_addon_sequence_reset_period-11.0.1.0.0.dist-info/RECORD
odoo11_addon_sequence_reset_period-11.0.1.0.0.dist-info/WHEEL
odoo11_addon_sequence_reset_period-11.0.1.0.0.dist-info/metadata.json
odoo11_addon_sequence_reset_period-11.0.1.0.0.dist-info/top_level.txt
